cores/__init__.py
cores/cache.py
cores/error_response.py
cores/commands/delete_queue.py
cores/component/__init__.py
cores/component/client.py
cores/component/firebase_service.py
cores/component/jwt.py
cores/component/mail_service.py
cores/component/memcache.py
cores/component/redis.py
cores/component/redis_cache.py
cores/component/s3.py
cores/component/sqlalchemy.py
cores/component/mongodb/database.py
cores/component/mongodb/service_base.py
cores/component/mongodb/service_base_contract.py
cores/config/__init__.py
cores/config/config.py
cores/config/database_config.py
cores/config/logging_config.py
cores/config/mail_config.py
cores/config/messaging_config.py
cores/config/s3_config.py
cores/config/sentry_config.py
cores/config/service_config.py
cores/config/settings.py
cores/config/system_integrator_config.py
cores/depends/authorization.py
cores/depends/mcp_depends.py
cores/enum/cache.py
cores/errors/base_error.py
cores/errors/common_error.py
cores/events/__init__.py
cores/events/event_bus.py
cores/events/interfaces.py
cores/events/publisher.py
cores/events/schemas/__init__.py
cores/events/schemas/base_event.py
cores/interface/index.py
cores/logger/__init__.py
cores/logger/context.py
cores/logger/enhanced_logging.py
cores/logger/health_check.py
cores/logger/logging.py
cores/logger/logging_setup.py
cores/logger/worker_logging.py
cores/middleware/auth.py
cores/middleware/context_middleware.py
cores/middleware/enhanced_logging_middleware.py
cores/middleware/error_handler.py
cores/middleware/exception.py
cores/middleware/index.py
cores/middleware/logging.py
cores/middleware/request_logging.py
cores/middleware/system_integrator_middleware.py
cores/model/base_error.py
cores/model/base_model.py
cores/model/error_model.py
cores/model/event.py
cores/model/paging.py
cores/model/profile.py
cores/model/system_integrator.py
cores/outbox/__init__.py
cores/outbox/models.py
cores/outbox/repository.py
cores/outbox/worker.py
cores/repository/mysql_sqlalchemy_repository.py
tterp_cores-0.4.0.dist-info/licenses/LICENSE
tterp_cores-0.4.0.dist-info/METADATA
tterp_cores-0.4.0.dist-info/WHEEL
tterp_cores-0.4.0.dist-info/top_level.txt
tterp_cores-0.4.0.dist-info/RECORD
