Metadata-Version: 2.4
Name: tterp-cores
Version: 0.4.0
Summary: Shared repository for microservices in ERP system
Author-email: Your Name <your.email@example.com>
License-Expression: MIT
Requires-Python: >=3.9
License-File: LICENSE
Requires-Dist: aio-pika==9.2.2
Requires-Dist: aiocache==0.12.2
Requires-Dist: aiomcache==0.8.2
Requires-Dist: aioredis==2.0.1
Requires-Dist: aiosqlite==0.19.0
Requires-Dist: alembic==1.8.1
Requires-Dist: asyncmy==0.2.10
Requires-Dist: autoflake==2.3.1
Requires-Dist: billiard==3.6.4.0
Requires-Dist: black==25.1.0
Requires-Dist: click-didyoumean==0.3.1
Requires-Dist: click-repl==0.3.0
Requires-Dist: colorama==0.4.6
Requires-Dist: cryptography==42.0.7
Requires-Dist: Faker==33.3.0
Requires-Dist: fastapi==0.115.6
Requires-Dist: flake8==7.1.2
Requires-Dist: fpdf==1.7.2
Requires-Dist: httpx==0.23.1
Requires-Dist: httpx-sse==0.4.0
Requires-Dist: kombu==5.4.1
Requires-Dist: openpyxl==3.1.2
Requires-Dist: pandas==2.2.2
Requires-Dist: pika==1.3.2
Requires-Dist: pip-tools==7.4.1
Requires-Dist: pydantic-settings==2.9.1
Requires-Dist: PyJWT==2.4.0
Requires-Dist: pylint-sqlalchemy==0.3.0
Requires-Dist: PyMySQL==1.0.2
Requires-Dist: pytest==7.4.4
Requires-Dist: pytest-asyncio==0.21.1
Requires-Dist: pytest-cov==6.1.1
Requires-Dist: pytest-mock==3.11.1
Requires-Dist: pytest-xdist==3.6.1
Requires-Dist: python-decouple==3.6
Requires-Dist: python-docx==0.8.11
Requires-Dist: python-jose==3.3.0
Requires-Dist: python-multipart==0.0.5
Requires-Dist: pythondi==1.2.4
Requires-Dist: redis==5.2.1
Requires-Dist: reportlab==4.3.1
Requires-Dist: sentry-sdk==1.28.1
Requires-Dist: SQLAlchemy-Utils==0.38.3
Requires-Dist: sse-starlette==2.3.6
Requires-Dist: Unidecode==1.3.8
Requires-Dist: uvicorn==0.18.2
Requires-Dist: xlrd==2.0.1
Requires-Dist: XlsxWriter==3.2.2
Dynamic: license-file
